{"cameraMode":{"drawMode":0,"name":"Shaded","section":"Shading Mode"},"sceneLighting":false,"audioPlay":false,"sceneViewState":{"showFog":true,"showMaterialUpdate":false,"showSkybox":false,"showFlares":true,"showImageEffects":true,"showParticleSystems":true},"in2DMode":false,"pivot":{"x":14.9127197265625,"y":3.9978039264678957,"z":-6.683534622192383},"rotation":{"x":-0.3627777099609375,"y":0.06896015256643295,"z":-0.026927391067147256,"w":-0.9289541244506836},"size":13.214746475219727,"orthographic":false}